setup.cfg
setup.py
StreamDecompressor/__init__.py
StreamDecompressor/archive.py
StreamDecompressor/guesser.py
StreamDecompressor.egg-info/PKG-INFO
StreamDecompressor.egg-info/SOURCES.txt
StreamDecompressor.egg-info/dependency_links.txt
StreamDecompressor.egg-info/requires.txt
StreamDecompressor.egg-info/top_level.txt
StreamDecompressor/decompressors/__init__.py
StreamDecompressor/decompressors/bzip2.py
StreamDecompressor/decompressors/gzip.py
StreamDecompressor/decompressors/lzma.py
StreamDecompressor/decompressors/p7zip.py
StreamDecompressor/decompressors/rar.py
StreamDecompressor/decompressors/tar.py
StreamDecompressor/decompressors/xz.py
StreamDecompressor/decompressors/zip.py