Metadata-Version: 1.1
Name: StreamDecompressor
Version: 2.1.post1
Summary: A simple module to decompress streams compressed multiple times
Home-page: https://github.com/cecton/StreamDecompressor
Author: Cecile Tonglet
Author-email: cecile.tonglet@gmail.com
License: GPLv2
Keywords: postgres database dump restore
Platform: UNKNOWN
Classifier: Development Status :: 5 - Production/Stable
Classifier: Topic :: System :: Archiving :: Compression
Classifier: License :: OSI Approved :: GNU General Public License v2 (GPLv2)
